trellens/__init__.py
trellens-0.0.0.dist-info/LICENSE
trellens-0.0.0.dist-info/WHEEL
trellens-0.0.0.dist-info/METADATA
trellens-0.0.0.dist-info/RECORD
