Metadata-Version: 2.1
Name: trellens
Version: 0.0.0
Summary: Short description of your project.
Author-email: blakeNaccarato <blake.naccarato+trellens@gmail.com>
Requires-Python: >=3.11
Project-URL: Home, https://github.com/blakeNaccarato/trellens
